certbot_dns_aliyun/__init__.py
certbot_dns_aliyun/dns_aliyun.py
certbot_dns_aliyun_lexicon-1.6.0.dev5.dist-info/LICENSE.txt
certbot_dns_aliyun_lexicon-1.6.0.dev5.dist-info/METADATA
certbot_dns_aliyun_lexicon-1.6.0.dev5.dist-info/WHEEL
certbot_dns_aliyun_lexicon-1.6.0.dev5.dist-info/entry_points.txt
certbot_dns_aliyun_lexicon-1.6.0.dev5.dist-info/top_level.txt
certbot_dns_aliyun_lexicon-1.6.0.dev5.dist-info/RECORD
