Metadata-Version: 2.1
Name: certbot-dns-aliyun-lexicon
Version: 1.6.0.dev5
Summary: Aliyun DNS Authenticator plugin for Certbot by lexicon
Home-page: https://github.com/xxy1991/certbot-dns-aliyun-lexicon
Author: xxy1991
Author-email: xxy@ori.fyi
License: Apache License 2.0
Platform: UNKNOWN
Classifier: Development Status :: 5 - Production/Stable
Classifier: Environment :: Plugins
Classifier: Intended Audience :: System Administrators
Classifier: License :: OSI Approved :: Apache Software License
Classifier: Operating System :: POSIX :: Linux
Classifier: Programming Language :: Python
Classifier: Programming Language :: Python :: 3
Classifier: Programming Language :: Python :: 3.5
Classifier: Programming Language :: Python :: 3.6
Classifier: Programming Language :: Python :: 3.7
Classifier: Programming Language :: Python :: 3.8
Classifier: Topic :: Internet :: WWW/HTTP
Classifier: Topic :: Security
Classifier: Topic :: System :: Installation/Setup
Classifier: Topic :: System :: Networking
Classifier: Topic :: System :: Systems Administration
Classifier: Topic :: Utilities
Requires-Python: >=3.5
Requires-Dist: acme (>=0.31.0)
Requires-Dist: acme (>=1.6.0)
Requires-Dist: certbot (>=1.1.0)
Requires-Dist: certbot (>=1.6.0)
Requires-Dist: dns-lexicon (>=2.2.1)
Requires-Dist: setuptools
Requires-Dist: tldextract
Requires-Dist: zope.interface
Requires-Dist: mock ; python_version < "3.3"
Provides-Extra: docs
Requires-Dist: Sphinx (>=1.0) ; extra == 'docs'
Requires-Dist: sphinx-rtd-theme ; extra == 'docs'
